unifi_discovery/__init__.py
unifi_discovery/py.typed
unifi_discovery-1.2.0.dist-info/LICENSE
unifi_discovery-1.2.0.dist-info/METADATA
unifi_discovery-1.2.0.dist-info/WHEEL
unifi_discovery-1.2.0.dist-info/RECORD
