Metadata-Version: 2.1
Name: unifi-discovery
Version: 1.2.0
Summary: Discover Unifi Devices
Home-page: https://github.com/uilibs/unifi-discovery
License: Apache-2.0
Author: J. Nick Koston
Author-email: nick@koston.org
Requires-Python: >=3.9,<4.0
Classifier: Development Status :: 2 - Pre-Alpha
Classifier: Intended Audience :: Developers
Classifier: License :: OSI Approved :: Apache Software License
Classifier: Natural Language :: English
Classifier: Operating System :: OS Independent
Classifier: Programming Language :: Python :: 3
Classifier: Programming Language :: Python :: 3.9
Classifier: Programming Language :: Python :: 3.10
Classifier: Programming Language :: Python :: 3.11
Classifier: Programming Language :: Python :: 3.12
Classifier: Topic :: Software Development :: Libraries
Provides-Extra: docs
Requires-Dist: Sphinx (>=5.0.0,<6.0.0) ; extra == "docs"
Requires-Dist: aiohttp (>=3.8.0)
Requires-Dist: myst-parser (>=0.17.0) ; extra == "docs"
Requires-Dist: pyroute2 (>=0.6.5)
Requires-Dist: sphinx-rtd-theme (>=1.0.0,<2.0.0) ; extra == "docs"
Project-URL: Bug Tracker, https://github.com/uilibs/unifi-discovery/issues
Project-URL: Changelog, https://unifi-discovery.readthedocs.io/changelog.html
Project-URL: Documentation, https://unifi-discovery.readthedocs.io
Project-URL: Repository, https://github.com/uilibs/unifi-discovery
